examples/__init__.py
tests/__init__.py
tests/create_3d_scatter_dashboard.py
tests/create_3d_scatter_plot.py
tests/create_actual_vs_predicted_distribution.py
tests/create_error_heatmap.py
tests/create_feature_importance_plot.py
tests/create_interactive_scatter_plot.py
tests/create_qq_plot.py
tests/create_residual_plots.py
tests/create_two_column_scatter_plot.py
tests/residual_plot_with_shapley.py
tests/visualize_advanced_regression_metrics.py
tests/visualize_regression_metrics.py
xai/__init__.py
xai/classification/__init__.py
xai/classification/models/__init__.py
xai/classification/visualizations/__init__.py
xai/datasets/__init__.py
xai/datasets/classification_data/__init__.py
xai/datasets/regression_data/Admission_Prediction.csv
xai/datasets/regression_data/__init__.py
xai/datasets/regression_data/bike_sharing_demand.csv
xai/datasets/regression_data/house_prices.csv
xai/datasets/reinforcement_learning_data/__init__.py
xai/datasets/unsupervised_data/__init__.py
xai/regression/__init__.py
xai/regression/models/__init__.py
xai/regression/models/admission_prediction_X_test.csv
xai/regression/models/admission_prediction_X_train.csv
xai/regression/models/admission_prediction_y_test.csv
xai/regression/models/admission_prediction_y_train.csv
xai/regression/models/bike_sharing_demand_X_test.csv
xai/regression/models/bike_sharing_demand_X_train.csv
xai/regression/models/bike_sharing_demand_y_test.csv
xai/regression/models/bike_sharing_demand_y_train.csv
xai/regression/models/lasso_regression_model.pkl
xai/regression/models/linear_regression_model.pkl
xai/regression/models/random_forest_model.pkl
xai/regression/models/support_vector_model.pkl
xai/regression/visualizations/__init__.py
xai/reinforcement_learning/__init__.py
xai/reinforcement_learning/models/__init__.py
xai/reinforcement_learning/visualizations/__init__.py
xai/unsupervised_learning/__init__.py
xai/unsupervised_learning/models/__init__.py
xai/unsupervised_learning/visualizations/__init__.py
xai_kit-0.0.9.dist-info/LICENSE
xai_kit-0.0.9.dist-info/METADATA
xai_kit-0.0.9.dist-info/WHEEL
xai_kit-0.0.9.dist-info/top_level.txt
xai_kit-0.0.9.dist-info/RECORD
