Metadata-Version: 2.1
Name: xai-kit
Version: 0.0.9
Summary: Explainable Artificial Intelligence (XAI) Library
Home-page: https://github.com/Zeed-Almelhem/XAI
Author: Zeed Almelhem
Author-email: info@zeed-almelhem.com
Keywords: xai,xaiz,explainable ai,interpretable ai,machine learning,deep learning,artificial intelligence,data science,model interpretability,model transparency,model explanation,model visualization,regression analysis,classification,supervised learning,unsupervised learning,reinforcement learning,data visualization,feature importance,regression metrics,model evaluation,machine learning library,python library,machine learning explainability,ai transparency,ai ethics,ai accountability,model expla
Classifier: Programming Language :: Python :: 3
Classifier: License :: OSI Approved :: MIT License
Classifier: Operating System :: OS Independent
License-File: LICENSE
Requires-Dist: matplotlib
Requires-Dist: pandas
Requires-Dist: seaborn
Requires-Dist: dash
Requires-Dist: dash-core-components
Requires-Dist: dash-html-components
Requires-Dist: plotly
Requires-Dist: numpy
Requires-Dist: scikit-learn
Requires-Dist: scipy
Requires-Dist: statsmodels
Requires-Dist: shap
